{
    "manifests": {
	    },
	       "https://alicia99813.github.io/Placement-Practice/manifests/Sumerian_clay_tablet.json": {
		    "provider": "The Univeristy of Cambridge"
	    },
	      "https://alicia99813.github.io/Placement-Practice/manifests/Aramaic_ostracon.json": {
		    "provider": "The Univeristy of Cambridge"
	    },
	       "https://alicia99813.github.io/Placement-Practice/manifests/Woodenmummylabel.json": {
		    "provider": "The Univeristy of Cambridge"
    },
    "windows": [
	    {
	        "id": "a",
                "manifestId": "https://alicia99813.github.io/Placement-Practice/manifests/Sumerian_clay_tablet.json",
                "canvasIndex": 0
            },
	    	{
                "id": "b",
                "manifestId": "https://alicia99813.github.io/Placement-Practice/manifests/Aramaic_ostracon.json",
                "canvasIndex": 0
            },
	      {
                "id": "c",
           	"manifestId": "https://alicia99813.github.io/Placement-Practice/manifests/Woodenmummylabel.json",
                "canvasIndex": 0
            }
    ],
     "workspace": {
        "layout": {
            "direction": "row",
            "first": "a",
            "second": {
                "first": "b",
                "second": "c",
                "direction": "row"
                                },
            "splitPercentage": 33.33
                        }
            }
}
